cc/__init__.py
cc/xmljson/__init__.py
cc/xmljson/__main__.py
cc.xmljson-0.2.1.dist-info/AUTHORS.rst
cc.xmljson-0.2.1.dist-info/LICENSE
cc.xmljson-0.2.1.dist-info/METADATA
cc.xmljson-0.2.1.dist-info/WHEEL
cc.xmljson-0.2.1.dist-info/top_level.txt
cc.xmljson-0.2.1.dist-info/RECORD
