Metadata-Version: 2.1
Name: cc.xmljson
Version: 0.2.1
Summary: Converts XML into JSON/Python dicts/arrays and vice-versa.
Home-page: https://github.com/uncertainty-cc/xmljson-Python
Author: Uncertainty.
Author-email: t_k_233@outlook.email
License: MIT
Classifier: Development Status :: 4 - Beta
Classifier: Intended Audience :: Developers
Classifier: Programming Language :: Python :: 3
Classifier: License :: OSI Approved :: MIT License
Classifier: Operating System :: OS Independent
Classifier: Topic :: Software Development
Classifier: Topic :: Software Development :: Libraries :: Python Modules
Requires-Python: >=3.6
License-File: LICENSE
License-File: AUTHORS.rst
